MANIFEST.in
README.txt
bootstrap.py
buildout.cfg
setup.cfg
setup.py
docs/HISTORY.txt
docs/INSTALL.txt
docs/LICENSE.GPL
docs/LICENSE.txt
plone/__init__.py
plone.contentratings.egg-info/PKG-INFO
plone.contentratings.egg-info/SOURCES.txt
plone.contentratings.egg-info/dependency_links.txt
plone.contentratings.egg-info/entry_points.txt
plone.contentratings.egg-info/namespace_packages.txt
plone.contentratings.egg-info/not-zip-safe
plone.contentratings.egg-info/requires.txt
plone.contentratings.egg-info/top_level.txt
plone/contentratings/README.txt
plone/contentratings/TODO.txt
plone/contentratings/__init__.py
plone/contentratings/assignment.py
plone/contentratings/assignment.txt
plone/contentratings/behaviors.py
plone/contentratings/catalog.py
plone/contentratings/category.py
plone/contentratings/category.txt
plone/contentratings/configure.zcml
plone/contentratings/interfaces.py
plone/contentratings/profiles.zcml
plone/contentratings/schema_extender.py
plone/contentratings/setuphandlers.py
plone/contentratings/tests.py
plone/contentratings/usei18ndude.sh
plone/contentratings/vocabs.py
plone/contentratings/vocabs.zcml
plone/contentratings/browser/__init__.py
plone/contentratings/browser/ajax.py
plone/contentratings/browser/category_manage.py
plone/contentratings/browser/configure.zcml
plone/contentratings/browser/controlpanel.py
plone/contentratings/browser/display_object.pt
plone/contentratings/browser/hidden_readonly_object.pt
plone/contentratings/browser/interfaces.py
plone/contentratings/browser/tests.py
plone/contentratings/browser/viewlets.py
plone/contentratings/browser/resources/contentratings.js
plone/contentratings/browser/resources/delete_icon.gif
plone/contentratings/browser/resources/ratings_icon.png
plone/contentratings/browser/stylesheets/main.css
plone/contentratings/exportimport/__init__.py
plone/contentratings/exportimport/configure.zcml
plone/contentratings/exportimport/exportimport.py
plone/contentratings/locales/plone.contentratings-manual.pot
plone/contentratings/locales/plone.contentratings.pot
plone/contentratings/locales/cs/LC_MESSAGES/plone.contentratings.po
plone/contentratings/locales/de/LC_MESSAGES/plone.contentratings.po
plone/contentratings/locales/es/LC_MESSAGES/plone.contentratings.po
plone/contentratings/locales/eu/LC_MESSAGES/plone.contentratings.po
