Metadata-Version: 1.1
Name: plone.contentratings
Version: 1.2.1
Summary: Plone support for the contentratings package
Home-page: https://github.com/collective/plone.contentratings
Author: Alec Mitchell
Author-email: apm13@columbia.edu
License: GPL
Keywords: plone ratings,dexterity,behaviour,behavior
Platform: UNKNOWN
Classifier: License :: OSI Approved :: GNU General Public License (GPL)
Classifier: Framework :: Plone
Classifier: Framework :: Plone :: 4.1
Classifier: Framework :: Plone :: 4.2
Classifier: Framework :: Plone :: 4.3
Classifier: Framework :: Zope2
Classifier: Programming Language :: Python
Classifier: Programming Language :: Python :: 2.6
Classifier: Programming Language :: Python :: 2.7
Classifier: Topic :: Software Development :: Libraries :: Python Modules
